mkdocs_multirepo/__init__.py
mkdocs_multirepo/demo/config.yml
mkdocs_multirepo/demo/images/icon-repo-1.png
mkdocs_multirepo/demo/images/icon-repo-2.png
mkdocs_multirepo/demo/images/search.svg
mkdocs_multirepo/demo/index.tpl
mkdocs_multirepo/demo/styles.css
mkdocs_multirepo-0.5.2.dist-info/LICENSE
mkdocs_multirepo-0.5.2.dist-info/METADATA
mkdocs_multirepo-0.5.2.dist-info/WHEEL
mkdocs_multirepo-0.5.2.dist-info/entry_points.txt
mkdocs_multirepo-0.5.2.dist-info/RECORD
