Metadata-Version: 2.1
Name: mkdocs-multirepo
Version: 0.5.2
Summary: 
License: MIT
Author: Lars Wilhelmer
Requires-Python: >=3.7,<4.0
Classifier: License :: OSI Approved :: MIT License
Classifier: Programming Language :: Python :: 3
Classifier: Programming Language :: Python :: 3.7
Classifier: Programming Language :: Python :: 3.8
Classifier: Programming Language :: Python :: 3.9
Classifier: Programming Language :: Python :: 3.10
Classifier: Programming Language :: Python :: 3.11
Classifier: Programming Language :: Python :: 3.12
Requires-Dist: beautifulsoup4 (>=4.9,<5.0)
Requires-Dist: click (>=8.1,<9.0)
Requires-Dist: pyyaml (>=6.0,<7.0)
